tty_html/__init__.py
tty_html/main.py
tty_html-1.0.2.dist-info/LICENSE
tty_html-1.0.2.dist-info/METADATA
tty_html-1.0.2.dist-info/WHEEL
tty_html-1.0.2.dist-info/entry_points.txt
tty_html-1.0.2.dist-info/top_level.txt
tty_html-1.0.2.dist-info/RECORD
