Metadata-Version: 2.2
Name: tty-html
Version: 1.0.2
Summary: [Pre]tty-HTML: A CLI parser for HTML. Pretty print HTML inputs to Unix stdout.
Author-email: "@bRuttaZz" <agrajpdas@gmail.com>
License:                     GNU GENERAL PUBLIC LICENSE
Project-URL: Homepage, https://github.com/bRuttaZz/tty-html
Project-URL: Issues, https://github.com/bRuttaZz/tty-html/issues
Project-URL: Repository, https://github.com/bRuttaZz/tty-html.git
Project-URL: Documentation, https://pypi.org/project/tty-html/
Keywords: pretty-html,html,pre-tty,CLI,Unix,prettify,commandline
Classifier: Development Status :: 5 - Production/Stable
Classifier: Intended Audience :: Developers
Classifier: Intended Audience :: Science/Research
Classifier: License :: OSI Approved :: MIT License
Classifier: Operating System :: POSIX
Classifier: Operating System :: POSIX :: Linux
Classifier: Operating System :: Unix
Classifier: Programming Language :: Python :: 3.10
Classifier: Programming Language :: Python :: 3.11
Classifier: Programming Language :: Python :: 3.12
Classifier: Programming Language :: Python :: 3.13
Classifier: Topic :: Terminals
Classifier: Topic :: Text Processing
Classifier: Topic :: Text Processing :: Markup
Classifier: Topic :: Text Processing :: Markup :: HTML
Classifier: Topic :: Software Development
Classifier: Topic :: Utilities
Classifier: Typing :: Typed
Classifier: Natural Language :: English
Requires-Python: >=3.10
License-File: LICENSE
